{"file":"jsys_back.png","frames":{
"back_jsys_baozhuang_png":{"x":0,"y":0,"w":589,"h":362,"offX":0,"offY":0,"sourceW":589,"sourceH":362},
"back_jsys_box_blue_png":{"x":936,"y":687,"w":70,"h":88,"offX":0,"offY":0,"sourceW":70,"sourceH":88},
"back_jsys_box_blue2_png":{"x":900,"y":587,"w":70,"h":88,"offX":0,"offY":0,"sourceW":70,"sourceH":88},
"back_jsys_box_light_png":{"x":898,"y":118,"w":86,"h":116,"offX":0,"offY":0,"sourceW":86,"sourceH":116},
"back_jsys_box_red_png":{"x":898,"y":0,"w":86,"h":116,"offX":0,"offY":0,"sourceW":86,"sourceH":116},
"back_jsys_box_yellow_png":{"x":0,"y":775,"w":70,"h":88,"offX":0,"offY":0,"sourceW":70,"sourceH":88},
"back_jsys_box_yellow1_png":{"x":828,"y":587,"w":70,"h":88,"offX":0,"offY":0,"sourceW":70,"sourceH":88},
"back_jsys_btn_png":{"x":733,"y":657,"w":41,"h":41,"offX":0,"offY":0,"sourceW":41,"sourceH":41},
"back_jsys_chat_png":{"x":0,"y":729,"w":452,"h":44,"offX":0,"offY":0,"sourceW":452,"sourceH":44},
"back_jsys_gold_png":{"x":670,"y":656,"w":61,"h":31,"offX":0,"offY":0,"sourceW":61,"sourceH":31},
"back_jsys_head_png":{"x":72,"y":775,"w":77,"h":77,"offX":0,"offY":0,"sourceW":77,"sourceH":77},
"back_jsys_light_png":{"x":591,"y":0,"w":305,"h":305,"offX":2,"offY":2,"sourceW":309,"sourceH":309},
"back_jsys_lightline_png":{"x":986,"y":0,"w":12,"h":685,"offX":0,"offY":0,"sourceW":12,"sourceH":685},
"back_jsys_mask_big_png":{"x":670,"y":538,"w":86,"h":116,"offX":0,"offY":0,"sourceW":86,"sourceH":116},
"back_jsys_mask_small_png":{"x":484,"y":364,"w":70,"h":88,"offX":0,"offY":0,"sourceW":70,"sourceH":88},
"back_jsys_open_png":{"x":591,"y":307,"w":382,"h":149,"offX":0,"offY":0,"sourceW":382,"sourceH":149},
"back_jsys_openstart_png":{"x":484,"y":538,"w":184,"h":188,"offX":0,"offY":0,"sourceW":184,"sourceH":188},
"back_jsys_record_png":{"x":898,"y":236,"w":54,"h":67,"offX":0,"offY":0,"sourceW":54,"sourceH":67},
"back_jsys_tips_png":{"x":484,"y":458,"w":469,"h":78,"offX":0,"offY":0,"sourceW":469,"sourceH":78},
"back_jsys_upzhuang_png":{"x":758,"y":538,"w":68,"h":117,"offX":0,"offY":0,"sourceW":68,"sourceH":117},
"back_jsys_zhuanglist_png":{"x":0,"y":364,"w":482,"h":363,"offX":0,"offY":0,"sourceW":482,"sourceH":363},
"back_jsys_zjlb_png":{"x":828,"y":538,"w":154,"h":47,"offX":0,"offY":0,"sourceW":154,"sourceH":47},
"back_jsys_zjlbline_png":{"x":484,"y":728,"w":450,"h":69,"offX":0,"offY":0,"sourceW":450,"sourceH":69}}}